bdlearn
