Metadata-Version: 2.1
Name: bdlearn
Version: 0.0.3
Summary: big data machine learning
Home-page: https://github.com/digbd/najia
Author: Dawei Zhang
Author-email: dawei-msn@hotmail.com
License: MIT Licence
Keywords: index,association
Platform: any
License-File: LICENSE
